AUTHORS.rst
MANIFEST.in
README.rst
duo.py
setup.py
test_duo.py
duo.egg-info/PKG-INFO
duo.egg-info/SOURCES.txt
duo.egg-info/dependency_links.txt
duo.egg-info/not-zip-safe
duo.egg-info/requires.txt
duo.egg-info/top_level.txt