Metadata-Version: 1.1
Name: duo
Version: 0.3.0
Summary: A powerful, dynamic, pythonic interface to AWS DynamoDB.
Home-page: http://github.com/eykd/duo
Author: David Eyk
Author-email: deyk@crossway.org
License: BSD
Platform: UNKNOWN
Classifier: Development Status :: 4 - Beta
Classifier: Environment :: Console
Classifier: Environment :: Web Environment
Classifier: Intended Audience :: Developers
Classifier: License :: OSI Approved :: BSD License
Classifier: Natural Language :: English
Classifier: Topic :: Database
Classifier: Topic :: Internet :: WWW/HTTP
Classifier: Topic :: Software Development :: Libraries
Classifier: Programming Language :: Python :: 2
Classifier: Programming Language :: Python :: 3.5
